timeteller/__init__.py
timeteller/__main__.py
timeteller/_cli_entry.py
timeteller/cli.py
timeteller/ext.py
timeteller/stdlib.py
timeteller-0.1.0rc3.dist-info/WHEEL
timeteller-0.1.0rc3.dist-info/entry_points.txt
timeteller-0.1.0rc3.dist-info/METADATA
timeteller-0.1.0rc3.dist-info/RECORD
