Metadata-Version: 2.3
Name: timeteller
Version: 0.1.0rc3
Summary: 
Author: oyghen
Author-email: oyghen <oyghen@duck.com>
Requires-Dist: typer>=0.20.1 ; extra == 'cli'
Requires-Dist: duckdb>=1.4.3 ; extra == 'ext'
Requires-Dist: python-dateutil>=2.9.0.post0 ; extra == 'ext'
Requires-Dist: tzdata>=2025.3 ; extra == 'ext'
Requires-Python: >=3.11
Provides-Extra: cli
Provides-Extra: ext
